<annotation><folder>open_images_volume</folder><filename>52686ac7c6da5fd4.jpg</filename><path>/mnt/open_images_volume/52686ac7c6da5fd4.jpg</path><source><database>Unknown</database></source><size><width>729</width><height>1024</height><depth>3</depth></size><segmented>0</segmented><object><name>Car</name><pose>Unspecified</pose><truncated>0</truncated><difficult>0</difficult><bndbox><xmin>39</xmin><ymin>490</ymin><xmax>704</xmax><ymax>707</ymax></bndbox></object><object><name>Car</name><pose>Unspecified</pose><truncated>0</truncated><difficult>0</difficult><bndbox><xmin>19</xmin><ymin>294</ymin><xmax>186</xmax><ymax>350</ymax></bndbox></object><object><name>Car</name><pose>Unspecified</pose><truncated>0</truncated><difficult>0</difficult><bndbox><xmin>344</xmin><ymin>721</ymin><xmax>580</xmax><ymax>881</ymax></bndbox></object></annotation>