<annotation><folder>open_images_volume</folder><filename>8966e5500c19ec50.jpg</filename><path>/mnt/open_images_volume/8966e5500c19ec50.jpg</path><source><database>Unknown</database></source><size><width>768</width><height>1024</height><depth>3</depth></size><segmented>0</segmented><object><name>Car</name><pose>Unspecified</pose><truncated>0</truncated><difficult>0</difficult><bndbox><xmin>0</xmin><ymin>640</ymin><xmax>43</xmax><ymax>688</ymax></bndbox></object><object><name>Car</name><pose>Unspecified</pose><truncated>0</truncated><difficult>0</difficult><bndbox><xmin>0</xmin><ymin>688</ymin><xmax>74</xmax><ymax>752</ymax></bndbox></object><object><name>Car</name><pose>Unspecified</pose><truncated>0</truncated><difficult>0</difficult><bndbox><xmin>48</xmin><ymin>641</ymin><xmax>120</xmax><ymax>734</ymax></bndbox></object></annotation>