<annotation><folder>open_images_volume</folder><filename>92db243ed8891c26.jpg</filename><path>/mnt/open_images_volume/92db243ed8891c26.jpg</path><source><database>Unknown</database></source><size><width>1024</width><height>672</height><depth>3</depth></size><segmented>0</segmented><object><name>Car</name><pose>Unspecified</pose><truncated>0</truncated><difficult>0</difficult><bndbox><xmin>182</xmin><ymin>583</ymin><xmax>200</xmax><ymax>611</ymax></bndbox></object><object><name>Car</name><pose>Unspecified</pose><truncated>0</truncated><difficult>0</difficult><bndbox><xmin>199</xmin><ymin>586</ymin><xmax>292</xmax><ymax>633</ymax></bndbox></object><object><name>Car</name><pose>Unspecified</pose><truncated>0</truncated><difficult>0</difficult><bndbox><xmin>267</xmin><ymin>587</ymin><xmax>330</xmax><ymax>618</ymax></bndbox></object><object><name>Car</name><pose>Unspecified</pose><truncated>0</truncated><difficult>0</difficult><bndbox><xmin>647</xmin><ymin>511</ymin><xmax>704</xmax><ymax>540</ymax></bndbox></object><object><name>Car</name><pose>Unspecified</pose><truncated>0</truncated><difficult>0</difficult><bndbox><xmin>693</xmin><ymin>513</ymin><xmax>734</xmax><ymax>538</ymax></bndbox></object><object><name>Car</name><pose>Unspecified</pose><truncated>0</truncated><difficult>0</difficult><bndbox><xmin>708</xmin><ymin>484</ymin><xmax>747</xmax><ymax>511</ymax></bndbox></object><object><name>Car</name><pose>Unspecified</pose><truncated>0</truncated><difficult>0</difficult><bndbox><xmin>780</xmin><ymin>520</ymin><xmax>821</xmax><ymax>554</ymax></bndbox></object></annotation>