<annotation><folder>open_images_volume</folder><filename>a17ca230f8f463dd.jpg</filename><path>/mnt/open_images_volume/a17ca230f8f463dd.jpg</path><source><database>Unknown</database></source><size><width>4000</width><height>3000</height><depth>3</depth></size><segmented>0</segmented><object><name>Car</name><pose>Unspecified</pose><truncated>0</truncated><difficult>0</difficult><bndbox><xmin>202</xmin><ymin>987</ymin><xmax>3715</xmax><ymax>2672</ymax></bndbox></object><object><name>Car</name><pose>Unspecified</pose><truncated>0</truncated><difficult>0</difficult><bndbox><xmin>2072</xmin><ymin>817</ymin><xmax>2175</xmax><ymax>847</ymax></bndbox></object><object><name>Car</name><pose>Unspecified</pose><truncated>0</truncated><difficult>0</difficult><bndbox><xmin>2675</xmin><ymin>795</ymin><xmax>3460</xmax><ymax>1127</ymax></bndbox></object><object><name>Car</name><pose>Unspecified</pose><truncated>0</truncated><difficult>0</difficult><bndbox><xmin>3295</xmin><ymin>830</ymin><xmax>3730</xmax><ymax>1085</ymax></bndbox></object><object><name>Car</name><pose>Unspecified</pose><truncated>0</truncated><difficult>0</difficult><bndbox><xmin>3652</xmin><ymin>837</ymin><xmax>3997</xmax><ymax>1170</ymax></bndbox></object></annotation>